LICENSE
MANIFEST.in
README.md
setup.py
iThenticate/__init__.py
iThenticate/test.py
iThenticate/API/Client.py
iThenticate/API/Exceptions.py
iThenticate/API/Helpers.py
iThenticate/API/__init__.py
iThenticate/API/Object/__init__.py
iThenticate/API/Object/data.py
iThenticate/API/Treasure/__init__.py
iThenticate/API/Treasure/documents.py
iThenticate/API/Treasure/folders.py
iThenticate/API/Treasure/groups.py
iThenticate/API/Treasure/reports.py
iThenticate/API/templates/add_document.xml
iThenticate/API/templates/add_folder.xml
iThenticate/API/templates/add_group.xml
iThenticate/API/templates/authentication.xml
iThenticate/API/templates/get.xml
iThenticate/API/templates/get_documents_pagination.xml
iThenticate/API/templates/list.xml
ithenticate_api_python_v1.egg-info/PKG-INFO
ithenticate_api_python_v1.egg-info/SOURCES.txt
ithenticate_api_python_v1.egg-info/dependency_links.txt
ithenticate_api_python_v1.egg-info/requires.txt
ithenticate_api_python_v1.egg-info/top_level.txt